Metadata-Version: 2.4
Name: feather-framework
Version: 0.8.5
Summary: An opinionated, batteries-included web framework for building production applications with AI.
Author: Roland Selmer
License-Expression: MIT
Project-URL: Homepage, https://github.com/RolandFlyBoy/Feather
Project-URL: Documentation, https://github.com/RolandFlyBoy/Feather#readme
Project-URL: Repository, https://github.com/RolandFlyBoy/Feather
Project-URL: Issues, https://github.com/RolandFlyBoy/Feather/issues
Keywords: flask,web framework,server-first,progressive enhancement,islands architecture,ai-friendly
Classifier: Development Status :: 3 - Alpha
Classifier: Environment :: Web Environment
Classifier: Framework :: Flask
Classifier: Intended Audience :: Developers
Classifier: Operating System :: OS Independent
Classifier: Programming Language :: Python :: 3
Classifier: Programming Language :: Python :: 3.11
Classifier: Programming Language :: Python :: 3.12
Classifier: Programming Language :: Python :: 3.13
Classifier: Topic :: Internet :: WWW/HTTP :: WSGI :: Application
Classifier: Topic :: Software Development :: Libraries :: Application Frameworks
Requires-Python: >=3.11
License-File: LICENSE
Requires-Dist: flask>=3.1.0
Requires-Dist: flask-sqlalchemy>=3.1.0
Requires-Dist: flask-migrate>=4.1.0
Requires-Dist: flask-login>=0.6.0
Requires-Dist: flask-wtf>=1.2.0
Requires-Dist: sqlalchemy>=2.0.0
Requires-Dist: alembic>=1.17.0
Requires-Dist: click>=8.1.0
Requires-Dist: python-dotenv>=1.0.0
Requires-Dist: werkzeug>=3.1.0
Requires-Dist: authlib>=1.6.0
Requires-Dist: requests>=2.32.0
Requires-Dist: psycopg2-binary>=2.9.0
Requires-Dist: google-cloud-storage>=3.0.0
Requires-Dist: reportlab>=4.4.0
Requires-Dist: redis>=7.0.0
Requires-Dist: rq>=2.0.0
Requires-Dist: resend>=2.0.0
Requires-Dist: gunicorn>=23.0.0
Requires-Dist: pytest>=8.0.0
Requires-Dist: pytest-cov>=6.0.0
Provides-Extra: dev
Requires-Dist: black>=25.0.0; extra == "dev"
Requires-Dist: ruff>=0.14.0; extra == "dev"
Dynamic: license-file
